{
  "users": [
    {
      "name": "Tun",
      "age": "11",
      "email": "tun@gmail.com",
      "password": "202cb962ac59075b964b07152d234b70",
      "id": "697RBIJmx",
      "avatar": "uploads\\6e92abb7ee787be5aecb7adfa36a46e7"
    },
    {
      "name": "long",
      "age": "13",
      "email": "long@gmail.com",
      "password": "202cb962ac59075b964b07152d234b70",
      "id": "Wyo6-jYzP",
      "avatar": "uploads\\6e92abb7ee787be5aecb7adfa36a46e7"
    },
    {
      "name": "Chung",
      "age": "19",
      "email": "chung@gmail.com",
      "password": "250cf8b51c773f3f8dc8b4be867a9a02",
      "id": "EF_7PFd5k",
      "avatar": "uploads\\6e92abb7ee787be5aecb7adfa36a46e7"
    },
    {
      "name": "abcd",
      "age": "17",
      "avatar": "uploads\\6e92abb7ee787be5aecb7adfa36a46e7",
      "email": "deptrai@gmail.com",
      "password": "202cb962ac59075b964b07152d234b70",
      "id": "ffQSk8MM2"
    },
    {
      "name": "liu",
      "age": "19",
      "avatar": "uploads\\6e92abb7ee787be5aecb7adfa36a46e7",
      "email": "lui@gmail.com",
      "password": "202cb962ac59075b964b07152d234b70",
      "id": "LbfyKfXWw"
    },
    {
      "name": "alex",
      "age": "18",
      "email": "alex@gmail.com",
      "password": "250cf8b51c773f3f8dc8b4be867a9a02",
      "id": "Jqtsf-kq8",
      "avatar": "uploads\\6e92abb7ee787be5aecb7adfa36a46e7"
    },
    {
      "name": "john",
      "age": "23",
      "email": "john@gmail.com",
      "password": "68053af2923e00204c3ca7c6a3150cf7",
      "id": "Ssrbxlfbu",
      "avatar": "uploads\\6e92abb7ee787be5aecb7adfa36a46e7"
    },
    {
      "name": "ty",
      "age": "42",
      "email": "y@gmail.com",
      "password": "202cb962ac59075b964b07152d234b70",
      "id": "XbhT_bpgB",
      "avatar": "uploads\\6e92abb7ee787be5aecb7adfa36a46e7"
    }
  ],
  "products": [
    {
      "name": "das",
      "id": "nwCmX-H_v"
    },
    {
      "name": "vay1",
      "id": "LWP7_xZdW"
    },
    {
      "name": "vay2",
      "id": "uFM6uRlWm"
    },
    {
      "name": "vay3",
      "id": "uFM6uRlWm"
    },
    {
      "name": "vay4",
      "id": "uFM6uRlWm"
    },
    {
      "name": "vay5",
      "id": "uFM6uRlWm"
    },
    {
      "name": "vay6",
      "id": "uFM6uRlWm"
    },
    {
      "name": "vay7",
      "id": "uFM6uRlWm"
    },
    {
      "name": "vay8",
      "id": "uFM6uRlWm"
    },
    {
      "name": "vay9",
      "id": "uFM6uRlWm"
    },
    {
      "name": "vay10",
      "id": "uFM6uRlWm"
    },
    {
      "name": "vay11",
      "id": "uFM6uRlWm"
    },
    {
      "name": "vay12",
      "id": "uFM6uRlWm"
    },
    {
      "name": "vay13",
      "id": "uFM6uRlWm"
    },
    {
      "name": "vay14",
      "id": "uFM6uRlWm"
    },
    {
      "name": "vay15",
      "id": "uFM6uRlWm"
    },
    {
      "name": "vay16",
      "id": "uFM6uRlWm"
    },
    {
      "name": "vay16",
      "id": "uFM6uRlWm"
    },
    {
      "name": "vay16",
      "id": "uFM6uRlWm"
    },
    {
      "name": "vay16",
      "id": "uFM6uRlWm"
    },
    {
      "name": "vay16",
      "id": "uFM6uRlWm"
    },
    {
      "name": "vay16",
      "id": "uFM6uRlWm"
    },
    {
      "name": "vay16",
      "id": "uFM6uRlWm"
    },
    {
      "name": "vay16",
      "id": "uFM6uRlWm"
    },
    {
      "name": "vay16",
      "id": "uFM6uRlWm"
    },
    {
      "name": "vay16",
      "id": "uFM6uRlWm"
    },
    {
      "name": "vay16",
      "id": "uFM6uRlWm"
    },
    {
      "name": "vay16",
      "id": "uFM6uRlWm"
    },
    {
      "name": "vay16",
      "id": "uFM6uRlWm"
    },
    {
      "name": "vaysadsa",
      "id": "uFM6uRlWm"
    },
    {
      "name": "vay sadhls",
      "id": "uFM6uRlWm"
    },
    {
      "name": "vay ádjka",
      "id": "uFM6uRlWm"
    },
    {
      "name": "vay ádjka",
      "id": "uFM6uRlWm"
    },
    {
      "name": "vay ádjka",
      "id": "uFM6uRlWm"
    },
    {
      "name": "vay ádjka",
      "id": "uFM6uRlWm"
    },
    {
      "name": "vay ádjka",
      "id": "uFM6uRlWm"
    },
    {
      "name": "vay ádjka",
      "id": "uFM6uRlWm"
    },
    {
      "name": "vay ádjka",
      "id": "uFM6uRlWm"
    },
    {
      "name": "vay ádjka",
      "id": "uFM6uRlWm"
    },
    {
      "name": "vay ádjka",
      "id": "uFM6uRlWm"
    },
    {
      "name": "vay ádjka",
      "id": "uFM6uRlWm"
    },
    {
      "name": "vay ádjka",
      "id": "uFM6uRlWm"
    },
    {
      "name": "vay ádjka",
      "id": "uFM6uRlWm"
    },
    {
      "name": "vay ádjka",
      "id": "uFM6uRlWm"
    },
    {
      "name": "vay ádjka",
      "id": "uFM6uRlWm"
    },
    {
      "name": "vay ádjka",
      "id": "uFM6uRlWm"
    },
    {
      "name": "vay ádjka",
      "id": "uFM6uRlWm"
    },
    {
      "name": "vay ádjka",
      "id": "uFM6uRlWm"
    },
    {
      "name": "vay ádjka",
      "id": "uFM6uRlWm"
    },
    {
      "name": "vay ádjka",
      "id": "uFM6uRlWm"
    },
    {
      "name": "vay ádjka",
      "id": "uFM6uRlWm"
    },
    {
      "name": "vay ádjka",
      "id": "uFM6uRlWm"
    },
    {
      "name": "vay ádjka",
      "id": "uFM6uRlWm"
    },
    {
      "name": "vay ádjka",
      "id": "uFM6uRlWm"
    },
    {
      "name": "vay ádjka",
      "id": "uFM6uRlWm"
    },
    {
      "name": "vay ádjka",
      "id": "uFM6uRlWm"
    },
    {
      "name": "vay ádjka",
      "id": "uFM6uRlWm"
    },
    {
      "name": "vay ádjka",
      "id": "uFM6uRlWm"
    },
    {
      "name": "vay ádjka",
      "id": "uFM6uRlWm"
    }
  ],
  "sessions": [
    {
      "id": "hkc0Mtf1M",
      "cart": {
        "nwCmX-H_v": 3,
        "LWP7_xZdW": 2,
        "uFM6uRlWm": 5
      }
    }
  ]
}